train_invaders/__init__.py
train_invaders/index.js
train_invaders/start.py
train_invaders/stop.py
train_invaders/view.txt
train_invaders-1.0.4.dist-info/LICENSE
train_invaders-1.0.4.dist-info/WHEEL
train_invaders-1.0.4.dist-info/METADATA
train_invaders-1.0.4.dist-info/RECORD
