Metadata-Version: 2.1
Name: train-invaders
Version: 1.0.4
Summary: Jupyter Notebook + Space Invaders!?
Home-page: https://github.com/aporia-ai/TrainInvaders
Author: Aporia
Requires-Python: >=3.6,<4.0
Classifier: Framework :: Jupyter
Classifier: Programming Language :: JavaScript
Classifier: Programming Language :: Python :: 3
Classifier: Programming Language :: Python :: 3.10
Classifier: Programming Language :: Python :: 3.6
Classifier: Programming Language :: Python :: 3.7
Classifier: Programming Language :: Python :: 3.8
Classifier: Programming Language :: Python :: 3.9
Classifier: Topic :: Games/Entertainment :: Arcade
Requires-Dist: ipython (<=7.16)
Project-URL: Repository, https://github.com/aporia-ai/TrainInvaders
